{
  "mappings": {
    "page": {
      "properties": {
        "model_key": {
          "type": "keyword"
        },
        "style_key": {
          "type": "keyword"
        },
        "size": {
          "type": "keyword"
        },
        "model_short": {
          "type": "keyword"
        },
        "is_sold_out": {
          "type": "keyword"
        },
        "available": {
          "type": "boolean"
        },
        "image_sets": {
          "type": "object"
        }
      }
    }
  }
}
